{
  "headline": "生而自由，永不驯服",
  "title": "普氏野马",
  "description": "普氏野马从未被驯化，自始至终按照自己的方式生存，被认为是地球上最后的野马。它们曾广泛分布于中亚地区，但在20世纪60年代，由于狩猎、栖息地丧失以及与家畜竞争，普氏野马在野外一度消失。幸运的是，少数在20世纪初被带入圈养环境的个体保存了这个物种的火种，也孕育了今天所有的普氏野马。",
  "ultraHighDef": "https://cn.bing.com/th?id=OHR.PrzewalskisHorse_ZH-CN5785609662_UHD.jpg",
  "imageUrl": "https://cn.bing.com/th?id=OHR.PrzewalskisHorse_ZH-CN5785609662_1920x1080.webp",
  "imageWallpaper": "https://cn.bing.com/th?id=OHR.PrzewalskisHorse_ZH-CN5785609662_1920x1200.jpg&rf=LaDigue_1920x1200.jpg",
  "mainText": "早在两万年前，欧洲的洞穴壁画中就已描绘出类似普氏野马的野生马匹。",
  "copyRight": "© Nemyrivskyi Viacheslav/Getty Images"
}